MANIFEST.in
README.rst
setup.py
django_userpreferences.egg-info/PKG-INFO
django_userpreferences.egg-info/SOURCES.txt
django_userpreferences.egg-info/dependency_links.txt
django_userpreferences.egg-info/requires.txt
django_userpreferences.egg-info/top_level.txt
preferences/__init__.py
preferences/admin.py
preferences/app_settings.py
preferences/fields.py
preferences/models.py
preferences/tests.py
preferences/urls.py
preferences/views.py
preferences/media/css/preferences.css
preferences/media/js/jquery-1.4.2.min.js
preferences/media/js/preferences.js
preferences/templates/preferences.html