Metadata-Version: 1.0
Name: django-userpreferences
Version: 0.1
Summary: Django application that allows you to easily store
Home-page: http://github.com/Narsil/django-userpreferences
Author: Nicolas Patry
Author-email: nicolas.patry@centraliens.net
License: UNKNOWN
Download-URL: http://github.com/Narsil/django-userpreferences/downloads/
Keywords: django preferences user settings profile
Platform: UNKNOWN
Classifier: Development Status :: 4 - Beta
Classifier: Intended Audience :: Developers
Classifier: License :: OSI Approved :: GNU Library or Lesser General Public License (LGPL)
Classifier: Topic :: Software Development :: Libraries :: Python Modules
Classifier: Environment :: Web Environment
Classifier: Topic :: Internet
Classifier: Operating System :: OS Independent
Classifier: Programming Language :: Python
Classifier: Framework :: Django
